viessmann_gridbox_connector/GridboxConnector.py
viessmann_gridbox_connector/__init__.py
viessmann_gridbox_connector/cli.py
viessmann_gridbox_connector/config.json
viessmann_gridbox_connector-1.7.2.dist-info/LICENSE
viessmann_gridbox_connector-1.7.2.dist-info/METADATA
viessmann_gridbox_connector-1.7.2.dist-info/WHEEL
viessmann_gridbox_connector-1.7.2.dist-info/entry_points.txt
viessmann_gridbox_connector-1.7.2.dist-info/top_level.txt
viessmann_gridbox_connector-1.7.2.dist-info/RECORD
