Metadata-Version: 2.1
Name: viessmann-gridbox-connector
Version: 1.7.2
Summary: Connector for Viessmann Gridbox to fetch live data from your Photovoltaic System
License-File: LICENSE
Requires-Dist: requests
Requires-Dist: authlib
